Metadata-Version: 2.1
Name: jupiterpy
Version: 0.2.0
Summary: A package to check Jupiter prices
Home-page: https://github.com/bomsauro/jupiterpy
Author: Bomsauro
Author-email: bomsauro@gmail.com
License: BSD 2-clause
Platform: UNKNOWN
